spai/__init__.py
spai/cli.py
spai/analytics/__init__.py
spai/analytics/forest_monitoring.py
spai/analytics/utils.py
spai/analytics/water_quality.py
spai/auth/__init__.py
spai/auth/auth.py
spai/auth/is_logged.py
spai/auth/logout.py
spai/auth/retrieve_credentials.py
spai/commands/__init__.py
spai/commands/auth.py
spai/commands/list.py
spai/commands/stop.py
spai/commands/workspace.py
spai/config/__init__.py
spai/config/config.py
spai/config/validate.py
spai/config/vars.py
spai/data/__init__.py
spai/data/climate/__init__.py
spai/data/ecosystems/__init__.py
spai/data/ecosystems/protected_areas.py
spai/data/fire/__init__.py
spai/data/fire/fwi/__init__.py
spai/data/fire/fwi/fwi_nasa.py
spai/data/hidrology/__init__.py
spai/data/hidrology/waterbodies.py
spai/data/hidrology/waterways.py
spai/data/satellite/__init__.py
spai/data/satellite/download.py
spai/data/satellite/explore.py
spai/data/satellite/load.py
spai/data/satellite/utils.py
spai/data/satellite/sentinelhub/SHCloudMaskDownloader.py
spai/data/satellite/sentinelhub/SHDEM30Downloader.py
spai/data/satellite/sentinelhub/SHDownloader.py
spai/data/satellite/sentinelhub/SHExplorer.py
spai/data/satellite/sentinelhub/SHS1Downloader.py
spai/data/satellite/sentinelhub/SHS2Downloader.py
spai/data/satellite/sentinelhub/SHS2L1CDownloader.py
spai/data/satellite/sentinelhub/SHS2L2ADownloader.py
spai/data/satellite/sentinelhub/SHS3OLCIDownloader.py
spai/data/satellite/sentinelhub/SHS3SLSTRDownloader.py
spai/data/satellite/sentinelhub/__init__.py
spai/data/satellite/sentinelhub/S5P/SHS5PCH4Downloader.py
spai/data/satellite/sentinelhub/S5P/SHS5PCODownloader.py
spai/data/satellite/sentinelhub/S5P/SHS5PDownloader.py
spai/data/satellite/sentinelhub/S5P/SHS5PHCHODownloader.py
spai/data/satellite/sentinelhub/S5P/SHS5PNO2Downloader.py
spai/data/satellite/sentinelhub/S5P/SHS5PO3Downloader.py
spai/data/satellite/sentinelhub/S5P/SHS5PSO2Downloader.py
spai/data/satellite/sentinelhub/S5P/__init__.py
spai/data/satellite/stac/STACDownloader.py
spai-2025.8.6.post2.dist-info/METADATA
spai-2025.8.6.post2.dist-info/WHEEL
spai-2025.8.6.post2.dist-info/entry_points.txt
spai-2025.8.6.post2.dist-info/RECORD
