Metadata-Version: 2.4
Name: spai
Version: 2025.8.6.post2
Author-email: Jan Sensio <it@earthpulse.es>
Requires-Python: >=3.12
Requires-Dist: minio>=7.1.15
Requires-Dist: pandas>=2.0.2
Requires-Dist: pillow>=10.2.0
Requires-Dist: pydantic>=2.0.3
Requires-Dist: pyjwt>=2.7.0
Requires-Dist: python-dotenv>=1.0.1
Requires-Dist: pyyaml>=6.0.0
Requires-Dist: requests>=2.31.0
Requires-Dist: rich>=13.7.0
Requires-Dist: schedule>=1.2.0
Requires-Dist: typer>=0.9.0
